camloop/__init__.py
camloop/camloop.py
pycamloop-0.0.4.dist-info/LICENSE
pycamloop-0.0.4.dist-info/METADATA
pycamloop-0.0.4.dist-info/WHEEL
pycamloop-0.0.4.dist-info/top_level.txt
pycamloop-0.0.4.dist-info/RECORD
