Metadata-Version: 2.1
Name: pycamloop
Version: 0.0.4
Summary: Forget the boilerplate from OpenCV camera loops and get to coding the interesting stuff
Home-page: https://github.com/glefundes/pycamloop
Author: Gabriel Lefundes
Author-email: lefundes.gabriel@gmail.com
License: MIT
Platform: UNKNOWN
Classifier: License :: OSI Approved :: MIT License
Classifier: Programming Language :: Python :: 3
Classifier: Programming Language :: Python :: 3.8
License-File: LICENSE
Requires-Dist: opencv-python (>=3.4)
Requires-Dist: imageio (>=2.9.0)
